{
  "centerselection": "",
  "copylinesdown": "",
  "copylinesup": "",
  "modifyNumberDown": "",
  "find": "",
  "fold": "",
  "foldall": "",
  "foldOther": "",
  "unfoldall": "",
  "unfold": "",
  "transposeletters": "",
  "toggleParentFoldWidget": "",
  "toggleFoldWidget": "",
  "touppercase": "",
  "tolowercase": "",
  "splitline": "",
  "sortlines": "",
  "selectlinestart": "",
  "selectlineend": "",
  "pageup": "",
  "pagedown": "",
  "removetolinestart": "",
  "removetolineend": "",
  "removewordright": "",
  "removewordleft": "",
  "overwrite": "",
  "outdent": "",
  "openCommandPallete": "",
  "gotopageup": "",
  "gotopagedown": "",
  "modifyNumberUp": "",
  "expandToMatching": "",
  "expandtoline": "Alt+Shift+l",
  "blockindent": "Alt+Shift+i",
  "blockoutdent": "Alt+Shift+o",
  "del": "Delete",
  "duplicateSelection": "Shift+Alt+d",
  "selectpageup": "Shift+Alt+Up",
  "selectpagedown": "Shift+Alt+Down",
  "findnext": "Alt+n",
  "findprevious": "Shift+Alt+n",
  "selecttomatching": "Alt+Shift+p",
  "selecttolinestart": "Shift+Cmd+Left",
  "selecttolineend": "Shift+Cmd+Right",
  "selecttoend": "Shift+Cmd+Down",
  "selecttostart": "Shift+Cmd+Up",
  "selectleft": "Shift+Left",
  "selectOrFindPrevious": "Alt+z",
  "selectOrFindNext": "Alt+y",
  "selectup": "Shift+Up",
  "selectdown": "Shift+Down",
  "removeline": "Alt+Shift+x",
  "redo": "Shift+Cmd+z",
  "gotoleft": "Left",
  "golineup": "Up",
  "movelinesup": "Alt+Shift+k",
  "movelinesdown": "Alt+Shift+j",
  "golinedown": "Down",
  "gotolinestart": "Cmd+Left||Ctrl+a",
  "gotostart": "Cmd+Up",
  "gotoright": "Right",
  "gotolineend": "Cmd+Right||Ctrl+e",
  "gotoend": "Cmd+Down",
  "selectall": "Alt+Shift+a",
  "saveSourceDoc": "Alt+w||Cmd+s"
}
